Workbook

Sheet Resumen
A1: Reporte de ventas · enero–junio 2026
A2: Todas las cifras se calculan con fórmulas sobre la hoja Datos.
A3: Indicador | B3: Valor | D3: Región | E3: Ingreso | F3: Participación | G3: Ventas Online
A4: Ingreso total | B4: =SUM(Datos!J2:J121) -> 77355 | D4: Norte | E4: =SUMIF(Datos!B2:B121,D4,Datos!J2:J121) -> 32580 | F4: =E4/$B$4 -> 0.4211751 | G4: =COUNTIFS(Datos!B2:B121,D4,Datos!C2:C121,"Online") -> 21
A5: Margen total | B5: =SUM(Datos!K2:K121) -> 27772 | D5: Sur | E5: =SUMIF(Datos!B2:B121,D5,Datos!J2:J121) -> 27175 | F5: =E5/$B$4 -> 0.35130244 | G5: =COUNTIFS(Datos!B2:B121,D5,Datos!C2:C121,"Online") -> 18
A6: Margen % | B6: =B5/B4 -> 0.3590201 | D6: Este | E6: =SUMIF(Datos!B2:B121,D6,Datos!J2:J121) -> 10510 | F6: =E6/$B$4 -> 0.13586711 | G6: =COUNTIFS(Datos!B2:B121,D6,Datos!C2:C121,"Online") -> 6
A7: N° de ventas | B7: =COUNTA(Datos!A2:A121) -> 120 | D7: Oeste | E7: =SUMIF(Datos!B2:B121,D7,Datos!J2:J121) -> 7090 | F7: =E7/$B$4 -> 0.091655355 | G7: =COUNTIFS(Datos!B2:B121,D7,Datos!C2:C121,"Online") -> 4
A8: Ticket promedio | B8: =AVERAGE(Datos!J2:J121) -> 644.625
A9: Venta máxima | B9: =MAX(Datos!J2:J121) -> 2400
A10: Ventas grandes (≥ 1000) | B10: =COUNTIF(Datos!J2:J121,">=1000") -> 27
A13: Vendedor | B13: Ingreso | C13: Meta | D13: Cumplimiento | E13: Estado
A14: Ana Torres | B14: =SUMIFS(Datos!J2:J121,Datos!D2:D121,A14) -> 8660 | C14: =VLOOKUP(A14,Vendedores!$A$2:$C$7,3,FALSE) -> 22000 | D14: =IFERROR(B14/C14,0) -> 0.39363636 | E14: =IF(D14>=1,"Cumplió","Por debajo") -> Por debajo
A15: Luis Pérez | B15: =SUMIFS(Datos!J2:J121,Datos!D2:D121,A15) -> 23920 | C15: =VLOOKUP(A15,Vendedores!$A$2:$C$7,3,FALSE) -> 18000 | D15: =IFERROR(B15/C15,0) -> 1.3288889 | E15: =IF(D15>=1,"Cumplió","Por debajo") -> Cumplió
A16: María Gómez | B16: =SUMIFS(Datos!J2:J121,Datos!D2:D121,A16) -> 11400 | C16: =VLOOKUP(A16,Vendedores!$A$2:$C$7,3,FALSE) -> 20000 | D16: =IFERROR(B16/C16,0) -> 0.57 | E16: =IF(D16>=1,"Cumplió","Por debajo") -> Por debajo
A17: Carlos Ruiz | B17: =SUMIFS(Datos!J2:J121,Datos!D2:D121,A17) -> 10510 | C17: =VLOOKUP(A17,Vendedores!$A$2:$C$7,3,FALSE) -> 20000 | D17: =IFERROR(B17/C17,0) -> 0.5255 | E17: =IF(D17>=1,"Cumplió","Por debajo") -> Por debajo
A18: Sofía Díaz | B18: =SUMIFS(Datos!J2:J121,Datos!D2:D121,A18) -> 7090 | C18: =VLOOKUP(A18,Vendedores!$A$2:$C$7,3,FALSE) -> 21000 | D18: =IFERROR(B18/C18,0) -> 0.33761905 | E18: =IF(D18>=1,"Cumplió","Por debajo") -> Por debajo
A19: Jorge Medina | B19: =SUMIFS(Datos!J2:J121,Datos!D2:D121,A19) -> 15775 | C19: =VLOOKUP(A19,Vendedores!$A$2:$C$7,3,FALSE) -> 17000 | D19: =IFERROR(B19/C19,0) -> 0.92794118 | E19: =IF(D19>=1,"Cumplió","Por debajo") -> Por debajo

Sheet Datos
A1: Fecha | B1: Región | C1: Canal | D1: Vendedor | E1: Producto | F1: Cantidad | G1: Precio | H1: Categoría | I1: Costo | J1: Total | K1: Margen | L1: Mes | M1: Tamaño
A2: 46023 | B2: Norte | C2: Tienda | D2: Luis Pérez | E2: Monitor 27 | F2: 3 | G2: 320 | H2: =VLOOKUP(E2,Productos!$A$2:$D$11,2,FALSE) -> Electrónica | I2: =VLOOKUP(E2,Productos!$A$2:$D$11,4,FALSE) -> 210 | J2: =F2*G2 -> 960 | K2: =F2*(G2-I2) -> 330 | L2: =MONTH(A2) -> 1 | M2: =IF(J2>=1000,"Grande",IF(J2>=300,"Mediana","Pequeña")) -> Mediana
A3: 46024 | B3: Este | C3: Online | D3: Carlos Ruiz | E3: Teclado mecánico | F3: 1 | G3: 85 | H3: =VLOOKUP(E3,Productos!$A$2:$D$11,2,FALSE) -> Accesorios | I3: =VLOOKUP(E3,Productos!$A$2:$D$11,4,FALSE) -> 50 | J3: =F3*G3 -> 85 | K3: =F3*(G3-I3) -> 35 | L3: =MONTH(A3) -> 1 | M3: =IF(J3>=1000,"Grande",IF(J3>=300,"Mediana","Pequeña")) -> Pequeña
A4: 46024 | B4: Sur | C4: Tienda | D4: María Gómez | E4: Audífonos BT | F4: 6 | G4: 95 | H4: =VLOOKUP(E4,Productos!$A$2:$D$11,2,FALSE) -> Electrónica | I4: =VLOOKUP(E4,Productos!$A$2:$D$11,4,FALSE) -> 55 | J4: =F4*G4 -> 570 | K4: =F4*(G4-I4) -> 240 | L4: =MONTH(A4) -> 1 | M4: =IF(J4>=1000,"Grande",IF(J4>=300,"Mediana","Pequeña")) -> Mediana
A5: 46027 | B5: Norte | C5: Online | D5: Luis Pérez | E5: Silla ergonómica | F5: 5 | G5: 260 | H5: =VLOOKUP(E5,Productos!$A$2:$D$11,2,FALSE) -> Oficina | I5: =VLOOKUP(E5,Productos!$A$2:$D$11,4,FALSE) -> 150 | J5: =F5*G5 -> 1300 | K5: =F5*(G5-I5) -> 550 | L5: =MONTH(A5) -> 1 | M5: =IF(J5>=1000,"Grande",IF(J5>=300,"Mediana","Pequeña")) -> Grande
A6: 46028 | B6: Norte | C6: Tienda | D6: Luis Pérez | E6: Audífonos BT | F6: 8 | G6: 95 | H6: =VLOOKUP(E6,Productos!$A$2:$D$11,2,FALSE) -> Electrónica | I6: =VLOOKUP(E6,Productos!$A$2:$D$11,4,FALSE) -> 55 | J6: =F6*G6 -> 760 | K6: =F6*(G6-I6) -> 320 | L6: =MONTH(A6) -> 1 | M6: =IF(J6>=1000,"Grande",IF(J6>=300,"Mediana","Pequeña")) -> Mediana
A7: 46029 | B7: Oeste | C7: Online | D7: Sofía Díaz | E7: Audífonos BT | F7: 3 | G7: 95 | H7: =VLOOKUP(E7,Productos!$A$2:$D$11,2,FALSE) -> Electrónica | I7: =VLOOKUP(E7,Productos!$A$2:$D$11,4,FALSE) -> 55 | J7: =F7*G7 -> 285 | K7: =F7*(G7-I7) -> 120 | L7: =MONTH(A7) -> 1 | M7: =IF(J7>=1000,"Grande",IF(J7>=300,"Mediana","Pequeña")) -> Pequeña
A8: 46029 | B8: Oeste | C8: Online | D8: Sofía Díaz | E8: Webcam HD | F8: 5 | G8: 60 | H8: =VLOOKUP(E8,Productos!$A$2:$D$11,2,FALSE) -> Accesorios | I8: =VLOOKUP(E8,Productos!$A$2:$D$11,4,FALSE) -> 32 | J8: =F8*G8 -> 300 | K8: =F8*(G8-I8) -> 140 | L8: =MONTH(A8) -> 1 | M8: =IF(J8>=1000,"Grande",IF(J8>=300,"Mediana","Pequeña")) -> Mediana
A9: 46032 | B9: Sur | C9: Online | D9: María Gómez | E9: Webcam HD | F9: 5 | G9: 60 | H9: =VLOOKUP(E9,Productos!$A$2:$D$11,2,FALSE) -> Accesorios | I9: =VLOOKUP(E9,Productos!$A$2:$D$11,4,FALSE) -> 32 | J9: =F9*G9 -> 300 | K9: =F9*(G9-I9) -> 140 | L9: =MONTH(A9) -> 1 | M9: =IF(J9>=1000,"Grande",IF(J9>=300,"Mediana","Pequeña")) -> Mediana
A10: 46035 | B10: Norte | C10: Online | D10: Luis Pérez | E10: Impresora láser | F10: 5 | G10: 210 | H10: =VLOOKUP(E10,Productos!$A$2:$D$11,2,FALSE) -> Oficina | I10: =VLOOKUP(E10,Productos!$A$2:$D$11,4,FALSE) -> 140 | J10: =F10*G10 -> 1050 | K10: =F10*(G10-I10) -> 350 | L10: =MONTH(A10) -> 1 | M10: =IF(J10>=1000,"Grande",IF(J10>=300,"Mediana","Pequeña")) -> Grande
A11: 46036 | B11: Norte | C11: Tienda | D11: Luis Pérez | E11: Tablet 10 | F11: 2 | G11: 380 | H11: =VLOOKUP(E11,Productos!$A$2:$D$11,2,FALSE) -> Electrónica | I11: =VLOOKUP(E11,Productos!$A$2:$D$11,4,FALSE) -> 270 | J11: =F11*G11 -> 760 | K11: =F11*(G11-I11) -> 220 | L11: =MONTH(A11) -> 1 | M11: =IF(J11>=1000,"Grande",IF(J11>=300,"Mediana","Pequeña")) -> Mediana
A12: 46041 | B12: Sur | C12: Online | D12: Jorge Medina | E12: Mouse inalámbrico | F12: 8 | G12: 25 | H12: =VLOOKUP(E12,Productos!$A$2:$D$11,2,FALSE) -> Accesorios | I12: =VLOOKUP(E12,Productos!$A$2:$D$11,4,FALSE) -> 12 | J12: =F12*G12 -> 200 | K12: =F12*(G12-I12) -> 104 | L12: =MONTH(A12) -> 1 | M12: =IF(J12>=1000,"Grande",IF(J12>=300,"Mediana","Pequeña")) -> Pequeña
A13: 46044 | B13: Norte | C13: Online | D13: Luis Pérez | E13: Mouse inalámbrico | F13: 4 | G13: 25 | H13: =VLOOKUP(E13,Productos!$A$2:$D$11,2,FALSE) -> Accesorios | I13: =VLOOKUP(E13,Productos!$A$2:$D$11,4,FALSE) -> 12 | J13: =F13*G13 -> 100 | K13: =F13*(G13-I13) -> 52 | L13: =MONTH(A13) -> 1 | M13: =IF(J13>=1000,"Grande",IF(J13>=300,"Mediana","Pequeña")) -> Pequeña
... A121: 46201 | B121: Norte | C121: Tienda | D121: Luis Pérez | E121: Teclado mecánico | F121: 5 | G121: 85 | H121: =VLOOKUP(E121,Productos!$A$2:$D$11,2,FALSE) -> Accesorios | I121: =VLOOKUP(E121,Productos!$A$2:$D$11,4,FALSE) -> 50 | J121: =F121*G121 -> 425 | K121: =F121*(G121-I121) -> 175 | L121: =MONTH(A121) -> 6 | M121: =IF(J121>=1000,"Grande",IF(J121>=300,"Mediana","Pequeña")) -> Mediana

Sheet Productos
A1: Producto | B1: Categoría | C1: Precio | D1: Costo
A2: Laptop Pro 14 | B2: Electrónica | C2: 1200 | D2: 900
A3: Monitor 27 | B3: Electrónica | C3: 320 | D3: 210
A4: Mouse inalámbrico | B4: Accesorios | C4: 25 | D4: 12
A5: Teclado mecánico | B5: Accesorios | C5: 85 | D5: 50
A6: Silla ergonómica | B6: Oficina | C6: 260 | D6: 150
A7: Escritorio ajustable | B7: Oficina | C7: 480 | D7: 300
A8: Impresora láser | B8: Oficina | C8: 210 | D8: 140
A9: Audífonos BT | B9: Electrónica | C9: 95 | D9: 55
A10: Webcam HD | B10: Accesorios | C10: 60 | D10: 32
A11: Tablet 10 | B11: Electrónica | C11: 380 | D11: 270

Sheet Vendedores
A1: Vendedor | B1: Región | C1: Meta
A2: Ana Torres | B2: Norte | C2: 22000
A3: Luis Pérez | B3: Norte | C3: 18000
A4: María Gómez | B4: Sur | C4: 20000
A5: Carlos Ruiz | B5: Este | C5: 20000
A6: Sofía Díaz | B6: Oeste | C6: 21000
A7: Jorge Medina | B7: Sur | C7: 17000

Sheet Tu turno
A1: Tareas para practicar (aprender haciendo)
A3: 1. En Datos, convierte la columna Mes en nombre del mes con =TEXTO(A2;"mmmm").
A4: 2. Crea una tabla dinámica (Insertar → Tabla dinámica) con Producto en filas, Canal en columnas y Total en valores.
A5: 3. Agrega una segmentación por Región a esa tabla dinámica.
A6: 4. En Resumen, calcula el ingreso de 'Laptop Pro 14' en el Norte con SUMAR.SI.CONJUNTO.
A7: 5. Usa BUSCARX para traer la región de cada vendedor en la hoja Datos.
A8: 6. Crea un gráfico de líneas del ingreso por mes.
A9: 7. Guarda, haz commit y push a GitHub: git add . && git commit -m "Excel: tabla dinámica y gráficos" && git push
